Metadata-Version: 1.1
Name: platformer1234
Version: 0.0.2
Summary: An demonstration of how to upload project to pypi.
Home-page: UNKNOWN
Author: Andy Z
Author-email: andyzhong147@gmail.com
License: MIT License
Keywords: tutorial
Platform: UNKNOWN
Classifier: Development Status :: 3 - Alpha
Classifier: License :: OSI Approved :: MIT License
